{  
    "alarm_id": 5,
    "name": "MAXIMUM ALLOWABLE FLOW RATE",
    "friendly_name": "High Water Flow Detected",
    "friendly_description": "Your Flo Valve seems to have higher than normally expected water flow rate. What would you like to do?",
    "system_mode": 2,
    "essential": true,
    "severity": 1,
    "mandatory": [
        2,
        3
    ],
    "optional": [],
    "icd_action": "Alert Notification. User decide action, valve closes automatically after timeout5",
    "user_actions": {
        "timeout": 300,
        "actions": [
            {
                "option": "Ignore For 2 hours",
                "display": "Snooze this alarm for 2 hours",
                "id": 1
            },
            {
                "option": "Midnight Cutoff",
                "display": "Snooze till Midnight",
                "id": 2
            },
            {
                "option": "Indefinite Override",
                "display": "Permanently stop notifications regarding this problem",
                "id": 3
            },
            {
                "option": "Accept As Normal",
                "display": "Accept As Normal",
                "id": 4
            }
        ]
    }
}